oteapi_dlite/__init__.py
oteapi_dlite/models/__init__.py
oteapi_dlite/models/session.py
oteapi_dlite/strategies/__init__.py
oteapi_dlite/strategies/generate.py
oteapi_dlite/strategies/mapping.py
oteapi_dlite/strategies/parse_json.py
oteapi_dlite/utils/__init__.py
oteapi_dlite/utils/exceptions.py
oteapi_dlite/utils/nputils.py
oteapi_dlite/utils/utils.py
oteapi_dlite_Mod-0.2.0.dist-info/LICENSE
oteapi_dlite_Mod-0.2.0.dist-info/METADATA
oteapi_dlite_Mod-0.2.0.dist-info/WHEEL
oteapi_dlite_Mod-0.2.0.dist-info/entry_points.txt
oteapi_dlite_Mod-0.2.0.dist-info/top_level.txt
oteapi_dlite_Mod-0.2.0.dist-info/RECORD
