Metadata-Version: 2.1
Name: oteapi-dlite-Mod
Version: 0.2.0
Summary: DLite plugin for OTEAPI.
Home-page: https://github.com/SINTEF/oteapi-dlite-Mod
Author: team4.0@sintef.no
Author-email: team4.0@sintef.no
Classifier: Programming Language :: Python :: 3
Classifier: Programming Language :: Python :: 3.9
Classifier: Programming Language :: Python :: 3.10
Classifier: License :: OSI Approved :: MIT License
Requires-Python: >=3.9
License-File: LICENSE
Requires-Dist: cachetools>=5.3.3
Requires-Dist: DLite-Python<1.0,>=0.4.5
Requires-Dist: influxdb-client>=1.44.0
Requires-Dist: jinja2>=3.1.4
Requires-Dist: numpy<2,>=1.21
Requires-Dist: oteapi-core~=0.7.0.dev2
Requires-Dist: pandas>=2.2.2
Requires-Dist: Pillow<11,>=9.0.1
Requires-Dist: rdflib>=7.0.0
Requires-Dist: SPARQLWrapper>=2.0.0
Requires-Dist: tripper==0.2.15
Provides-Extra: dev
Requires-Dist: otelib~=0.5.0.dev0; extra == "dev"
Requires-Dist: pylint~=3.1; extra == "dev"
Requires-Dist: pytest~=8.1; extra == "dev"
Requires-Dist: pytest-cov~=4.1; extra == "dev"
Requires-Dist: pyyaml>=5.0; extra == "dev"
Requires-Dist: griffe<1.0; extra == "dev"
Requires-Dist: invoke~=2.2; extra == "dev"
Requires-Dist: mike~=2.0; extra == "dev"
Requires-Dist: mkdocs~=1.5; extra == "dev"
Requires-Dist: mkdocs-awesome-pages-plugin~=2.9; extra == "dev"
Requires-Dist: mkdocs-material~=9.5; extra == "dev"
Requires-Dist: mkdocstrings[python]~=0.24.1; extra == "dev"
Requires-Dist: pre-commit~=3.6; extra == "dev"
Provides-Extra: docs
Requires-Dist: griffe<1.0; extra == "docs"
Requires-Dist: invoke~=2.2; extra == "docs"
Requires-Dist: mike~=2.0; extra == "docs"
Requires-Dist: mkdocs~=1.5; extra == "docs"
Requires-Dist: mkdocs-awesome-pages-plugin~=2.9; extra == "docs"
Requires-Dist: mkdocs-material~=9.5; extra == "docs"
Requires-Dist: mkdocstrings[python]~=0.24.1; extra == "docs"
Requires-Dist: pre-commit~=3.6; extra == "docs"
